{
  "$schema": "https://json-schema.org/draft/2020-12/schema",
  "$id": "https://techlib.cz/specification/ccmm/documentation/schema.json",
  "title": "Documentation",
  "description": "A textual resource intended for human consumption that contains information about the data service.",
  "type": "object",
  "required": [

  ],
  "properties": {
    "label": {
      "title": "Label",
      "description": "Documentation label",
      "type": "array",
      "items": {
        "title": "Language tagged string",
        "type": "object",
        "required": [
          "@value",
          "@language"
        ],
        "properties": {
          "@value": {
            "title": "Text v daném jazyce",
            "type": "string"
          },
          "@language": {
            "title": "Jazyk textu",
            "type": "string"
          }
        }
      }
    }
  }
}