{
  "$schema": "https://json-schema.org/draft/2020-12/schema",
  "$id": "https://techlib.cz/specification/ccmm/dataset/schema.json",
  "title": "Dataset",
  "description": "A collection of data, published or curated by a single source, and available for access or download in one or more representations.",
  "type": "object",
  "required": [
    "descriptions",
    "other_languages",
    "primary_language",
    "title",
    "identifier"
  ],
  "properties": {
    "id": {
      "type": "string",
      "format": "iri"
    },
    "type": {
      "oneOf": [
        {
          "const": "Datová sada"
        },
        {
          "type": "array",
          "contains": {
            "const": "Datová sada"
          },
          "items": {
            "type": "string"
          }
        }
      ]
    },
    "publication_year": {
      "title": "Publication year",
      "description": "The year when the item was or will be made publicly available.",
      "type": "string"
    },
    "descriptions": {
      "title": "Description",
      "description": "A free-text account of the Dataset.",
      "type": "array",
      "items": {
        "title": "String",
        "type": "string"
      }
    },
    "version": {
      "title": "Version",
      "description": "The version indicator (name or identifier) of a resource.",
      "type": "string"
    },
    "other_languages": {
      "title": "Other language",
      "description": "The primary language of the resource.",
      "type": "array",
      "items": {
        "title": "String",
        "type": "string"
      }
    },
    "primary_language": {
      "title": "Other language",
      "description": "The primary language of the resource.",
      "type": "string"
    },
    "alternate_titles": {
      "title": "Alternate title",
      "type": "array",
      "items": {
        "title": "String",
        "type": "string"
      }
    },
    "abstract": {
      "title": "Abstract",
      "description": "Dataset abstract.",
      "type": "string"
    },
    "resource_type": {
      "title": "Resource type",
      "description": "A description of the resource. ",
      "type": "string",
      "format": "iri"
    },
    "title": {
      "title": "Title",
      "description": "A name given to the resource.",
      "type": "string"
    },
    "identifier": {
      "title": "Identifier",
      "description": "The Identifier is a unique string that identifies a resource. For DataCite, this MUST be a DIgital Object Identifier (DOI). The format should be 10.21384/foo.",
      "type": "string",
      "format": "iri"
    },
    "locations": {
      "title": "has location",
      "description": "The geographical area covered by the dataset.",
      "type": "array",
      "items": {
        "title": "Location",
        "description": "Spatial region, named place or geometry representation of a place related to the dataset. ",
        "type": "object",
        "required": [

        ],
        "properties": {
          "id": {
            "type": "string",
            "format": "iri"
          },
          "type": {
            "oneOf": [
              {
                "const": "Location"
              },
              {
                "type": "array",
                "contains": {
                  "const": "Location"
                },
                "items": {
                  "type": "string"
                }
              }
            ]
          },
          "bbox": {
            "title": "bbox",
            "description": "Bounding box of the location geometry.",
            "type": "string"
          },
          "location_names": {
            "title": "Location name",
            "description": "Name of the spatial location.",
            "type": "array",
            "items": {
              "title": "String",
              "type": "string"
            }
          },
          "relations_to_dataset": {
            "title": "Relation to dataset",
            "description": "Type of relation of the spatial location to the dataset.",
            "type": "array",
            "items": {
              "title": "URI, IRI, URL",
              "type": "string",
              "format": "iri"
            }
          },
          "geometry": {
            "title": "geometry",
            "description": "The corresponding geometry for a resource.",
            "type": "string",
            "format": "iri"
          },
          "related_objects_identifiers": {
            "title": "has related object identifier",
            "description": "Relation to the existing spatial object.",
            "type": "array",
            "items": {
              "title": "Resource",
              "description": "Resource represents any resource, physical or digital, that is related to the described dataset. ",
              "type": "object",
              "required": [

              ],
              "properties": {
                "id": {
                  "type": "string",
                  "format": "iri"
                },
                "type": {
                  "title": "Type",
                  "description": "A description of the resource. Gets the value from controlled list https://datacite-metadata-schema.readthedocs.io/en/4.6/appendices/appendix-1/resourceTypeGeneral/.",
                  "type": "string",
                  "format": "iri"
                },
                "relation_type": {
                  "title": "Relation type",
                  "description": "Type of the relation between Dataset and related resource.",
                  "type": "string",
                  "format": "iri"
                },
                "title": {
                  "title": "Title",
                  "description": "A name given to the Catalogue Record.",
                  "type": "string"
                },
                "identifier": {
                  "title": "Identifier",
                  "description": "An unambiguous reference to the resource within a given context.",
                  "type": "string",
                  "format": "iri"
                },
                "qualified_relations": {
                  "title": "qualified relation",
                  "description": "Attachment of resource to the relationship.",
                  "type": "array",
                  "items": {
                    "title": "Resource to Agent Relationship",
                    "description": "An association class for attaching additional information to a relationship between Dataset and Agent.",
                    "type": "object",
                    "required": [
                      "roles",
                      "relations"
                    ],
                    "properties": {
                      "id": {
                        "type": "string",
                        "format": "iri"
                      },
                      "type": {
                        "oneOf": [
                          {
                            "const": "Resource to Agent Relationship"
                          },
                          {
                            "type": "array",
                            "contains": {
                              "const": "Resource to Agent Relationship"
                            },
                            "items": {
                              "type": "string"
                            }
                          }
                        ]
                      },
                      "roles": {
                        "title": "had role",
                        "description": "The function of an entity or agent with respect to another entity or resource.",
                        "type": "array",
                        "items": {
                          "type": "string",
                          "format": "iri"
                        }
                      },
                      "relations": {
                        "title": "relation",
                        "type": "array",
                        "items": {
                          "title": "Agent",
                          "description": "Any entity carrying out actions with respect to the entities Catalogue and the Catalogued Resources.",
                          "type": "object",
                          "required": [

                          ],
                          "properties": {
                            "id": {
                              "type": "string",
                              "format": "iri"
                            },
                            "type": {
                              "oneOf": [
                                {
                                  "const": "Agent"
                                },
                                {
                                  "type": "array",
                                  "contains": {
                                    "const": "Agent"
                                  },
                                  "items": {
                                    "type": "string"
                                  }
                                }
                              ]
                            },
                            "external_identifiers": {
                              "title": "External identifier",
                              "description": "External identifer of an Agent.",
                              "type": "array",
                              "items": {
                                "title": "String",
                                "type": "string"
                              }
                            },
                            "contact_points": {
                              "title": "contact point",
                              "description": "Relevant contact information for the catalogued resource. Use of vCard is recommended.",
                              "type": "array",
                              "items": {
                                "title": "Contact details",
                                "description": "Contact details such as telephone, e-mail address etc.",
                                "type": "object",
                                "required": [

                                ],
                                "properties": {
                                  "id": {
                                    "type": "string",
                                    "format": "iri"
                                  },
                                  "type": {
                                    "oneOf": [
                                      {
                                        "const": "Contact details"
                                      },
                                      {
                                        "type": "array",
                                        "contains": {
                                          "const": "Contact details"
                                        },
                                        "items": {
                                          "type": "string"
                                        }
                                      }
                                    ]
                                  },
                                  "phone": {
                                    "title": "Phone",
                                    "description": "Code of the data box.",
                                    "type": "array",
                                    "items": {
                                      "title": "String",
                                      "type": "string"
                                    }
                                  },
                                  "email": {
                                    "title": "Email",
                                    "description": "Email address.",
                                    "type": "array",
                                    "items": {
                                      "title": "String",
                                      "type": "string"
                                    }
                                  },
                                  "data_box": {
                                    "title": "Data box",
                                    "description": "Phone number",
                                    "type": "array",
                                    "items": {
                                      "title": "String",
                                      "type": "string"
                                    }
                                  },
                                  "addresses": {
                                    "title": "has address",
                                    "description": "To specify the components of the delivery address for the object",
                                    "type": "array",
                                    "items": {
                                      "type": "string",
                                      "format": "iri"
                                    }
                                  }
                                }
                              }
                            }
                          }
                        }
                      }
                    }
                  }
                },
                "time_references": {
                  "title": "has time reference",
                  "type": "array",
                  "items": {
                    "title": "Time reference",
                    "description": "A date on which something relative to the resource has happened.",
                    "type": "object",
                    "required": [

                    ],
                    "properties": {
                      "id": {
                        "type": "string",
                        "format": "iri"
                      },
                      "type": {
                        "oneOf": [
                          {
                            "const": "Time reference"
                          },
                          {
                            "type": "array",
                            "contains": {
                              "const": "Time reference"
                            },
                            "items": {
                              "type": "string"
                            }
                          }
                        ]
                      },
                      "date_information": {
                        "title": "Date information",
                        "description": "Additional information to the date in text form.",
                        "type": "string"
                      },
                      "date_type": {
                        "title": "Date type",
                        "description": "Type of the date.",
                        "type": "string",
                        "format": "iri"
                      },
                      "date": {
                        "title": "Date",
                        "description": "A point or period of time associated with an event in the lifecycle of the resource.",
                        "type": "string",
                        "format": "date"
                      }
                    }
                  }
                }
              }
            }
          }
        }
      }
    },
    "provenance": {
      "title": "provenance",
      "description": "A statement about the lineage of a Dataset.",
      "type": "array",
      "items": {
        "type": "string",
        "format": "iri"
      }
    },
    "qualified_relations": {
      "title": "qualified relation",
      "description": "Attachment of resource to the relationship.",
      "type": "array",
      "items": {
        "title": "Resource to Agent Relationship",
        "description": "An association class for attaching additional information to a relationship between Dataset and Agent.",
        "type": "object",
        "required": [
          "roles",
          "relations"
        ],
        "properties": {
          "id": {
            "type": "string",
            "format": "iri"
          },
          "type": {
            "oneOf": [
              {
                "const": "Resource to Agent Relationship"
              },
              {
                "type": "array",
                "contains": {
                  "const": "Resource to Agent Relationship"
                },
                "items": {
                  "type": "string"
                }
              }
            ]
          },
          "roles": {
            "title": "had role",
            "description": "The function of an entity or agent with respect to another entity or resource.",
            "type": "array",
            "items": {
              "type": "string",
              "format": "iri"
            }
          },
          "relations": {
            "title": "relation",
            "type": "array",
            "items": {
              "title": "Agent",
              "description": "Any entity carrying out actions with respect to the entities Catalogue and the Catalogued Resources.",
              "type": "object",
              "required": [

              ],
              "properties": {
                "id": {
                  "type": "string",
                  "format": "iri"
                },
                "type": {
                  "oneOf": [
                    {
                      "const": "Agent"
                    },
                    {
                      "type": "array",
                      "contains": {
                        "const": "Agent"
                      },
                      "items": {
                        "type": "string"
                      }
                    }
                  ]
                },
                "external_identifiers": {
                  "title": "External identifier",
                  "description": "External identifer of an Agent.",
                  "type": "array",
                  "items": {
                    "title": "String",
                    "type": "string"
                  }
                },
                "contact_points": {
                  "title": "contact point",
                  "description": "Relevant contact information for the catalogued resource. Use of vCard is recommended.",
                  "type": "array",
                  "items": {
                    "title": "Contact details",
                    "description": "Contact details such as telephone, e-mail address etc.",
                    "type": "object",
                    "required": [

                    ],
                    "properties": {
                      "id": {
                        "type": "string",
                        "format": "iri"
                      },
                      "type": {
                        "oneOf": [
                          {
                            "const": "Contact details"
                          },
                          {
                            "type": "array",
                            "contains": {
                              "const": "Contact details"
                            },
                            "items": {
                              "type": "string"
                            }
                          }
                        ]
                      },
                      "phone": {
                        "title": "Phone",
                        "description": "Code of the data box.",
                        "type": "array",
                        "items": {
                          "title": "String",
                          "type": "string"
                        }
                      },
                      "email": {
                        "title": "Email",
                        "description": "Email address.",
                        "type": "array",
                        "items": {
                          "title": "String",
                          "type": "string"
                        }
                      },
                      "data_box": {
                        "title": "Data box",
                        "description": "Phone number",
                        "type": "array",
                        "items": {
                          "title": "String",
                          "type": "string"
                        }
                      },
                      "addresses": {
                        "title": "has address",
                        "description": "To specify the components of the delivery address for the object",
                        "type": "array",
                        "items": {
                          "type": "string",
                          "format": "iri"
                        }
                      }
                    }
                  }
                }
              }
            }
          }
        }
      }
    },
    "time_references": {
      "title": "has time reference",
      "type": "array",
      "items": {
        "title": "Time reference",
        "description": "A date on which something relative to the resource has happened.",
        "type": "object",
        "required": [

        ],
        "properties": {
          "id": {
            "type": "string",
            "format": "iri"
          },
          "type": {
            "oneOf": [
              {
                "const": "Time reference"
              },
              {
                "type": "array",
                "contains": {
                  "const": "Time reference"
                },
                "items": {
                  "type": "string"
                }
              }
            ]
          },
          "date_information": {
            "title": "Date information",
            "description": "Additional information to the date in text form.",
            "type": "string"
          },
          "date_type": {
            "title": "Date type",
            "description": "Type of the date.",
            "type": "string",
            "format": "iri"
          },
          "date": {
            "title": "Date",
            "description": "A point or period of time associated with an event in the lifecycle of the resource.",
            "type": "string",
            "format": "date"
          }
        }
      }
    },
    "subjects": {
      "title": "has subject",
      "type": "array",
      "items": {
        "title": "Subject",
        "description": "Subject, keyword, classification code, or key phrase describing the resource.",
        "type": "object",
        "required": [
          "title"
        ],
        "properties": {
          "id": {
            "type": "string",
            "format": "iri"
          },
          "type": {
            "oneOf": [
              {
                "const": "Subject"
              },
              {
                "type": "array",
                "contains": {
                  "const": "Subject"
                },
                "items": {
                  "type": "string"
                }
              }
            ]
          },
          "definition": {
            "title": "Definition",
            "description": "Definition of the subject.",
            "type": "string"
          },
          "title": {
            "title": "Title",
            "description": "Title of the subject",
            "type": "string"
          },
          "classification_code": {
            "title": "Classification code",
            "description": "The classification code used for the subject term in the subject scheme.",
            "type": "string"
          },
          "in_subject_scheme": {
            "title": "in subject scheme",
            "type": "string",
            "format": "iri"
          }
        }
      }
    },
    "validation_results": {
      "title": "has validation result",
      "type": "array",
      "items": {
        "type": "string",
        "format": "iri"
      }
    },
    "distributions": {
      "title": "has distribution",
      "type": "array",
      "items": {
        "title": "Distribution",
        "description": "A specific representation of a dataset. A dataset might be available in multiple serializations that may differ in various ways, including natural language, media-type or format, schematic organization, temporal and spatial resolution, level of detail or profiles (which might specify any or all of the above).",
        "type": "object",
        "required": [

        ],
        "properties": {
          "id": {
            "type": "string",
            "format": "iri"
          },
          "type": {
            "oneOf": [
              {
                "const": "Distribuce"
              },
              {
                "type": "array",
                "contains": {
                  "const": "Distribuce"
                },
                "items": {
                  "type": "string"
                }
              }
            ]
          },
          "title": {
            "title": "Title",
            "description": "A name given to the distribution.",
            "type": "string"
          }
        }
      }
    },
    "funding_references": {
      "title": "has funding reference",
      "type": "array",
      "items": {
        "title": "Funding reference",
        "description": "Information about financial support (funding) for the resource being registered.",
        "type": "object",
        "required": [

        ],
        "properties": {
          "id": {
            "type": "string",
            "format": "iri"
          },
          "type": {
            "oneOf": [
              {
                "const": "Funding reference"
              },
              {
                "type": "array",
                "contains": {
                  "const": "Funding reference"
                },
                "items": {
                  "type": "string"
                }
              }
            ]
          },
          "funding_program": {
            "title": "Funding program",
            "description": "Reference to the specific funding program.",
            "type": "string",
            "format": "iri"
          },
          "award_title": {
            "title": "Award title",
            "description": " The human readable title or name of the award (grant).",
            "type": "string"
          },
          "local_identifier": {
            "title": "Local identifier",
            "description": "The code assigned by the funder to a sponsored award (grant).",
            "type": "string"
          },
          "funders": {
            "title": "has funder",
            "type": "array",
            "items": {
              "title": "Funder identifier",
              "description": "Uniquely identifies a funding entity, according to various types.",
              "type": "object",
              "required": [
                "funder_identifier_type"
              ],
              "properties": {
                "id": {
                  "type": "string",
                  "format": "iri"
                },
                "type": {
                  "oneOf": [
                    {
                      "const": "Funder identifier"
                    },
                    {
                      "type": "array",
                      "contains": {
                        "const": "Funder identifier"
                      },
                      "items": {
                        "type": "string"
                      }
                    }
                  ]
                },
                "funder_identifier_scheme_uri": {
                  "title": "Funder identifier scheme URI",
                  "description": "The URI of the funder identifier scheme.",
                  "type": "string",
                  "format": "iri"
                },
                "funder_identifier_type": {
                  "title": "Funder identifier type",
                  "description": "The type of the funderIdentifier.",
                  "type": "string",
                  "format": "iri"
                }
              }
            }
          }
        }
      }
    },
    "terms_of_use": {
      "title": "has terms of use",
      "type": "array",
      "items": {
        "title": "Terms of use",
        "description": "Terms of use defines overall conditions and rights regarding access and usage  of dataset. ",
        "type": "object",
        "required": [

        ],
        "properties": {
          "id": {
            "type": "string",
            "format": "iri"
          },
          "type": {
            "oneOf": [
              {
                "const": "Terms of use"
              },
              {
                "type": "array",
                "contains": {
                  "const": "Terms of use"
                },
                "items": {
                  "type": "string"
                }
              }
            ]
          },
          "description": {
            "title": "Description",
            "description": "Descriptive text on details of rights and licensing.",
            "type": "string"
          },
          "license": {
            "title": "License",
            "description": "Information about licensing details of the resource.",
            "type": "string",
            "format": "iri"
          },
          "access_rights": {
            "title": "Access rights",
            "description": "Information about who access the resource or an indication of its security status.",
            "type": "array",
            "items": {
              "title": "String",
              "type": "string"
            }
          },
          "contact_persons": {
            "title": "has contact person",
            "description": "Contact person for the further details about the terms of use.",
            "type": "array",
            "items": {
              "title": "Agent",
              "description": "Any entity carrying out actions with respect to the entities Catalogue and the Catalogued Resources.",
              "type": "object",
              "required": [

              ],
              "properties": {
                "id": {
                  "type": "string",
                  "format": "iri"
                },
                "type": {
                  "oneOf": [
                    {
                      "const": "Agent"
                    },
                    {
                      "type": "array",
                      "contains": {
                        "const": "Agent"
                      },
                      "items": {
                        "type": "string"
                      }
                    }
                  ]
                },
                "external_identifiers": {
                  "title": "External identifier",
                  "description": "External identifer of an Agent.",
                  "type": "array",
                  "items": {
                    "title": "String",
                    "type": "string"
                  }
                },
                "contact_points": {
                  "title": "contact point",
                  "description": "Relevant contact information for the catalogued resource. Use of vCard is recommended.",
                  "type": "array",
                  "items": {
                    "title": "Contact details",
                    "description": "Contact details such as telephone, e-mail address etc.",
                    "type": "object",
                    "required": [

                    ],
                    "properties": {
                      "id": {
                        "type": "string",
                        "format": "iri"
                      },
                      "type": {
                        "oneOf": [
                          {
                            "const": "Contact details"
                          },
                          {
                            "type": "array",
                            "contains": {
                              "const": "Contact details"
                            },
                            "items": {
                              "type": "string"
                            }
                          }
                        ]
                      },
                      "phone": {
                        "title": "Phone",
                        "description": "Code of the data box.",
                        "type": "array",
                        "items": {
                          "title": "String",
                          "type": "string"
                        }
                      },
                      "email": {
                        "title": "Email",
                        "description": "Email address.",
                        "type": "array",
                        "items": {
                          "title": "String",
                          "type": "string"
                        }
                      },
                      "data_box": {
                        "title": "Data box",
                        "description": "Phone number",
                        "type": "array",
                        "items": {
                          "title": "String",
                          "type": "string"
                        }
                      },
                      "addresses": {
                        "title": "has address",
                        "description": "To specify the components of the delivery address for the object",
                        "type": "array",
                        "items": {
                          "type": "string",
                          "format": "iri"
                        }
                      }
                    }
                  }
                }
              }
            }
          }
        }
      }
    },
    "related_resources": {
      "title": "has related resource",
      "type": "array",
      "items": {
        "title": "Resource",
        "description": "Resource represents any resource, physical or digital, that is related to the described dataset. ",
        "type": "object",
        "required": [

        ],
        "properties": {
          "id": {
            "type": "string",
            "format": "iri"
          },
          "type": {
            "title": "Type",
            "description": "A description of the resource. Gets the value from controlled list https://datacite-metadata-schema.readthedocs.io/en/4.6/appendices/appendix-1/resourceTypeGeneral/.",
            "type": "string",
            "format": "iri"
          },
          "relation_type": {
            "title": "Relation type",
            "description": "Type of the relation between Dataset and related resource.",
            "type": "string",
            "format": "iri"
          },
          "title": {
            "title": "Title",
            "description": "A name given to the Catalogue Record.",
            "type": "string"
          },
          "identifier": {
            "title": "Identifier",
            "description": "An unambiguous reference to the resource within a given context.",
            "type": "string",
            "format": "iri"
          },
          "qualified_relations": {
            "title": "qualified relation",
            "description": "Attachment of resource to the relationship.",
            "type": "array",
            "items": {
              "title": "Resource to Agent Relationship",
              "description": "An association class for attaching additional information to a relationship between Dataset and Agent.",
              "type": "object",
              "required": [
                "roles",
                "relations"
              ],
              "properties": {
                "id": {
                  "type": "string",
                  "format": "iri"
                },
                "type": {
                  "oneOf": [
                    {
                      "const": "Resource to Agent Relationship"
                    },
                    {
                      "type": "array",
                      "contains": {
                        "const": "Resource to Agent Relationship"
                      },
                      "items": {
                        "type": "string"
                      }
                    }
                  ]
                },
                "roles": {
                  "title": "had role",
                  "description": "The function of an entity or agent with respect to another entity or resource.",
                  "type": "array",
                  "items": {
                    "type": "string",
                    "format": "iri"
                  }
                },
                "relations": {
                  "title": "relation",
                  "type": "array",
                  "items": {
                    "title": "Agent",
                    "description": "Any entity carrying out actions with respect to the entities Catalogue and the Catalogued Resources.",
                    "type": "object",
                    "required": [

                    ],
                    "properties": {
                      "id": {
                        "type": "string",
                        "format": "iri"
                      },
                      "type": {
                        "oneOf": [
                          {
                            "const": "Agent"
                          },
                          {
                            "type": "array",
                            "contains": {
                              "const": "Agent"
                            },
                            "items": {
                              "type": "string"
                            }
                          }
                        ]
                      },
                      "external_identifiers": {
                        "title": "External identifier",
                        "description": "External identifer of an Agent.",
                        "type": "array",
                        "items": {
                          "title": "String",
                          "type": "string"
                        }
                      },
                      "contact_points": {
                        "title": "contact point",
                        "description": "Relevant contact information for the catalogued resource. Use of vCard is recommended.",
                        "type": "array",
                        "items": {
                          "title": "Contact details",
                          "description": "Contact details such as telephone, e-mail address etc.",
                          "type": "object",
                          "required": [

                          ],
                          "properties": {
                            "id": {
                              "type": "string",
                              "format": "iri"
                            },
                            "type": {
                              "oneOf": [
                                {
                                  "const": "Contact details"
                                },
                                {
                                  "type": "array",
                                  "contains": {
                                    "const": "Contact details"
                                  },
                                  "items": {
                                    "type": "string"
                                  }
                                }
                              ]
                            },
                            "phone": {
                              "title": "Phone",
                              "description": "Code of the data box.",
                              "type": "array",
                              "items": {
                                "title": "String",
                                "type": "string"
                              }
                            },
                            "email": {
                              "title": "Email",
                              "description": "Email address.",
                              "type": "array",
                              "items": {
                                "title": "String",
                                "type": "string"
                              }
                            },
                            "data_box": {
                              "title": "Data box",
                              "description": "Phone number",
                              "type": "array",
                              "items": {
                                "title": "String",
                                "type": "string"
                              }
                            },
                            "addresses": {
                              "title": "has address",
                              "description": "To specify the components of the delivery address for the object",
                              "type": "array",
                              "items": {
                                "type": "string",
                                "format": "iri"
                              }
                            }
                          }
                        }
                      }
                    }
                  }
                }
              }
            }
          },
          "time_references": {
            "title": "has time reference",
            "type": "array",
            "items": {
              "title": "Time reference",
              "description": "A date on which something relative to the resource has happened.",
              "type": "object",
              "required": [

              ],
              "properties": {
                "id": {
                  "type": "string",
                  "format": "iri"
                },
                "type": {
                  "oneOf": [
                    {
                      "const": "Time reference"
                    },
                    {
                      "type": "array",
                      "contains": {
                        "const": "Time reference"
                      },
                      "items": {
                        "type": "string"
                      }
                    }
                  ]
                },
                "date_information": {
                  "title": "Date information",
                  "description": "Additional information to the date in text form.",
                  "type": "string"
                },
                "date_type": {
                  "title": "Date type",
                  "description": "Type of the date.",
                  "type": "string",
                  "format": "iri"
                },
                "date": {
                  "title": "Date",
                  "description": "A point or period of time associated with an event in the lifecycle of the resource.",
                  "type": "string",
                  "format": "date"
                }
              }
            }
          }
        }
      }
    },
    "alternate_identifiers": {
      "title": "has alternate identifier",
      "type": "array",
      "items": {
        "title": "Alternate identifier",
        "description": "An identifier other than the primary Identifier applied to the resource being registered. This may be any alphanumeric string which is unique within its domain of issue. May be used for local identifiers, a serial number of an instrument or an inventory number. The AlternateIdentifier should be an additional identifier for the same instance of the resource (i.e., same location, same file).",
        "type": "object",
        "required": [

        ],
        "properties": {
          "id": {
            "type": "string",
            "format": "iri"
          },
          "type": {
            "oneOf": [
              {
                "const": "Alternate identifier"
              },
              {
                "type": "array",
                "contains": {
                  "const": "Alternate identifier"
                },
                "items": {
                  "type": "string"
                }
              }
            ]
          },
          "alternate_identifier_type": {
            "title": "alternate identifier type",
            "description": "The type of the Alternate identifier.",
            "type": "string"
          }
        }
      }
    }
  }
}